docs/.gitignore
docs/Makefile
docs/api.rst
docs/attribution.rst
docs/changelog.rst
docs/cli.rst
docs/conf.py
docs/config.rst
docs/contributorguide.rst
docs/environment.yml
docs/faqs.rst
docs/hacks.py
docs/index.rst
docs/install.rst
docs/integration_tests.rst
docs/intro.rst
docs/latex.rst
docs/layout.rst
docs/logging.rst
docs/migrating.rst
docs/overleaf.rst
docs/projects.json
docs/projects.rst.jinja
docs/quickbuild.rst
docs/quickstart.rst
docs/reproducibility.rst
docs/snakefile.rst
docs/zenodo.rst
docs/_static/actions_tab.png
docs/_static/article-abstract.png
docs/_static/badges.png
docs/_static/default_ms.png
docs/_static/default_ms_with_figure.png
docs/_static/logo.png
docs/_static/overview.png
docs/_static/workflow_permissions.png
docs/_static/zenodo_dois.png
docs/_static/css/custom.css
docs/api/.gitignore
showyourwork/__init__.py
showyourwork/__main__.py
showyourwork/_showyourwork_version.py
showyourwork/config.py
showyourwork/git.py
showyourwork/gitapi.py
showyourwork/logging.py
showyourwork/overleaf.py
showyourwork/patches.py
showyourwork/paths.py
showyourwork/subproc.py
showyourwork/userrules.py
showyourwork/zenodo.py
showyourwork/cli/__init__.py
showyourwork/cli/main.py
showyourwork/cli/commands/__init__.py
showyourwork/cli/commands/build.py
showyourwork/cli/commands/cache.py
showyourwork/cli/commands/clean.py
showyourwork/cli/commands/preprocess.py
showyourwork/cli/commands/run_snakemake.py
showyourwork/cli/commands/setup.py
showyourwork/cli/commands/tarball.py
showyourwork/cli/commands/zenodo.py
showyourwork/cookiecutter-showyourwork/cookiecutter.json
showyourwork/cookiecutter-showyourwork/{{ cookiecutter.repo }}/.gitignore
showyourwork/cookiecutter-showyourwork/{{ cookiecutter.repo }}/LICENSE
showyourwork/cookiecutter-showyourwork/{{ cookiecutter.repo }}/README.md
showyourwork/cookiecutter-showyourwork/{{ cookiecutter.repo }}/Snakefile
showyourwork/cookiecutter-showyourwork/{{ cookiecutter.repo }}/environment.yml
showyourwork-0.4.3.dist-info/LICENSE
showyourwork-0.4.3.dist-info/METADATA
showyourwork-0.4.3.dist-info/WHEEL
showyourwork-0.4.3.dist-info/entry_points.txt
showyourwork-0.4.3.dist-info/top_level.txt
showyourwork-0.4.3.dist-info/RECORD
