Metadata-Version: 2.1
Name: showyourwork
Version: 0.4.3
Summary: A workflow for open-source scientific articles
Home-page: https://github.com/showyourwork/showyourwork
Author: Rodrigo Luger
Author-email: rodluger@gmail.com
License: MIT
Requires-Python: >=3.8
License-File: LICENSE
Requires-Dist: graphviz (>=0.19.1)
Requires-Dist: jinja2 (>=3.0.3)
Requires-Dist: pyyaml (>=6.0)
Requires-Dist: requests (>=2.25.1)
Requires-Dist: click (>=8.1.3)
Requires-Dist: cookiecutter (>=2.1.1)
Requires-Dist: packaging (>=21.3)
Requires-Dist: snakemake (==7.15.2)
Provides-Extra: tests
Requires-Dist: pytest (>=7.0.0) ; extra == 'tests'
Requires-Dist: pytest-asyncio-cooperative (>=0.28.0) ; extra == 'tests'
